setup.py
pyrise/__init__.py
pyrise.egg-info/PKG-INFO
pyrise.egg-info/SOURCES.txt
pyrise.egg-info/dependency_links.txt
pyrise.egg-info/requires.txt
pyrise.egg-info/top_level.txt