Metadata-Version: 1.0
Name: pyrise
Version: 0.5.3
Summary: Python wrapper for 37Signals Highrise
Home-page: http://github.com/feedmagnet/pyrise
Author: Jason Ford
Author-email: jason@feedmagnet.com
License: MIT License
Keywords: python 37signals highrise api wrapper feedmagnet
Platform: UNKNOWN
